{
   "runs" : [
      {
         "OS" : "linux",
         "abstract" : "Generate fuzz and corpus-driven test harnesses",
         "dir" : "/home/runner/work/App-Test-Generator/App-Test-Generator",
         "finish" : 1762907624.01603,
         "name" : "App-Test-Generator",
         "perl" : "5.40.3",
         "run" : "-e",
         "start" : 1762907624.01565,
         "version" : "0.15"
      },
      {
         "OS" : "linux",
         "abstract" : "Generate fuzz and corpus-driven test harnesses",
         "dir" : "/home/runner/work/App-Test-Generator/App-Test-Generator",
         "finish" : 1762907624.20253,
         "name" : "App-Test-Generator",
         "perl" : "5.40.3",
         "run" : "-e",
         "start" : 1762907624.20224,
         "version" : "0.15"
      },
      {
         "OS" : "linux",
         "abstract" : "Generate fuzz and corpus-driven test harnesses",
         "dir" : "/home/runner/work/App-Test-Generator/App-Test-Generator",
         "finish" : 1762907624.37621,
         "name" : "App-Test-Generator",
         "perl" : "5.40.3",
         "run" : "-e",
         "start" : 1762907624.37583,
         "version" : "0.15"
      },
      {
         "OS" : "linux",
         "abstract" : "Generate fuzz and corpus-driven test harnesses",
         "dir" : "/home/runner/work/App-Test-Generator/App-Test-Generator",
         "finish" : 1762907624.54851,
         "name" : "App-Test-Generator",
         "perl" : "5.40.3",
         "run" : "-e",
         "start" : 1762907624.54803,
         "version" : "0.15"
      },
      {
         "OS" : "linux",
         "abstract" : "Generate fuzz and corpus-driven test harnesses",
         "dir" : "/home/runner/work/App-Test-Generator/App-Test-Generator",
         "finish" : 1762907624.72526,
         "name" : "App-Test-Generator",
         "perl" : "5.40.3",
         "run" : "-e",
         "start" : 1762907624.72498,
         "version" : "0.15"
      },
      {
         "OS" : "linux",
         "abstract" : "Generate fuzz and corpus-driven test harnesses",
         "dir" : "/home/runner/work/App-Test-Generator/App-Test-Generator",
         "finish" : 1762907624.90353,
         "name" : "App-Test-Generator",
         "perl" : "5.40.3",
         "run" : "-e",
         "start" : 1762907624.90327,
         "version" : "0.15"
      },
      {
         "OS" : "linux",
         "abstract" : "Generate fuzz and corpus-driven test harnesses",
         "dir" : "/home/runner/work/App-Test-Generator/App-Test-Generator",
         "finish" : 1762907625.07927,
         "name" : "App-Test-Generator",
         "perl" : "5.40.3",
         "run" : "-e",
         "start" : 1762907625.07901,
         "version" : "0.15"
      },
      {
         "OS" : "linux",
         "abstract" : "Generate fuzz and corpus-driven test harnesses",
         "dir" : "/home/runner/work/App-Test-Generator/App-Test-Generator",
         "finish" : 1762907625.24951,
         "name" : "App-Test-Generator",
         "perl" : "5.40.3",
         "run" : "-e",
         "start" : 1762907625.24924,
         "version" : "0.15"
      },
      {
         "OS" : "linux",
         "abstract" : "Generate fuzz and corpus-driven test harnesses",
         "dir" : "/home/runner/work/App-Test-Generator/App-Test-Generator",
         "finish" : 1762907625.44353,
         "name" : "App-Test-Generator",
         "perl" : "5.40.3",
         "run" : "-e",
         "start" : 1762907625.4287,
         "version" : "0.15"
      },
      {
         "OS" : "linux",
         "abstract" : "Generate fuzz and corpus-driven test harnesses",
         "dir" : "/home/runner/work/App-Test-Generator/App-Test-Generator",
         "finish" : 1762907625.67301,
         "name" : "App-Test-Generator",
         "perl" : "5.40.3",
         "run" : "-e",
         "start" : 1762907625.67251,
         "version" : "0.15"
      },
      {
         "OS" : "linux",
         "abstract" : "Generate fuzz and corpus-driven test harnesses",
         "dir" : "/home/runner/work/App-Test-Generator/App-Test-Generator",
         "finish" : 1762907633.15322,
         "name" : "App-Test-Generator",
         "perl" : "5.40.3",
         "run" : "-e",
         "start" : 1762907625.87453,
         "version" : "0.15"
      },
      {
         "OS" : "linux",
         "abstract" : "Generate fuzz and corpus-driven test harnesses",
         "dir" : "/home/runner/work/App-Test-Generator/App-Test-Generator",
         "finish" : 1762907626.02272,
         "name" : "App-Test-Generator",
         "perl" : "5.40.3",
         "run" : "-e",
         "start" : 1762907626.02262,
         "version" : "0.15"
      },
      {
         "OS" : "linux",
         "abstract" : "Generate fuzz and corpus-driven test harnesses",
         "dir" : "/home/runner/work/App-Test-Generator/App-Test-Generator",
         "finish" : 1762907626.34131,
         "name" : "App-Test-Generator",
         "perl" : "5.40.3",
         "run" : "t/10-compile.t",
         "start" : 1762907626.34028,
         "version" : "0.15"
      },
      {
         "OS" : "linux",
         "abstract" : "Generate fuzz and corpus-driven test harnesses",
         "dir" : "/home/runner/work/App-Test-Generator/App-Test-Generator",
         "finish" : 1762907626.89211,
         "name" : "App-Test-Generator",
         "perl" : "5.40.3",
         "run" : "t/30-basics.t",
         "start" : 1762907626.82239,
         "version" : "0.15"
      },
      {
         "OS" : "linux",
         "abstract" : "Generate fuzz and corpus-driven test harnesses",
         "dir" : "/home/runner/work/App-Test-Generator/App-Test-Generator",
         "finish" : 1762907627.56517,
         "name" : "App-Test-Generator",
         "perl" : "5.40.3",
         "run" : "t/40-more.t",
         "start" : 1762907627.3939,
         "version" : "0.15"
      },
      {
         "OS" : "linux",
         "abstract" : "Generate fuzz and corpus-driven test harnesses",
         "dir" : "/home/runner/work/App-Test-Generator/App-Test-Generator",
         "finish" : 1762907628.7411,
         "name" : "App-Test-Generator",
         "perl" : "5.40.3",
         "run" : "t/abs.t",
         "start" : 1762907628.08321,
         "version" : "0.15"
      },
      {
         "OS" : "linux",
         "abstract" : "Generate fuzz and corpus-driven test harnesses",
         "dir" : "/home/runner/work/App-Test-Generator/App-Test-Generator",
         "finish" : 1762907628.64949,
         "name" : "App-Test-Generator",
         "perl" : "5.40.3",
         "run" : "t/tmp_abs.t",
         "start" : 1762907628.63007,
         "version" : "0.15"
      },
      {
         "OS" : "linux",
         "abstract" : "Generate fuzz and corpus-driven test harnesses",
         "dir" : "/home/runner/work/App-Test-Generator/App-Test-Generator",
         "finish" : 1762907629.22423,
         "name" : "App-Test-Generator",
         "perl" : "5.40.3",
         "run" : "t/conf-corpus.t",
         "start" : 1762907629.22389,
         "version" : "0.15"
      },
      {
         "OS" : "linux",
         "abstract" : "Generate fuzz and corpus-driven test harnesses",
         "dir" : "/home/runner/work/App-Test-Generator/App-Test-Generator",
         "finish" : 1762907629.64332,
         "name" : "App-Test-Generator",
         "perl" : "5.40.3",
         "run" : "t/conf-fuzz.t",
         "start" : 1762907629.64294,
         "version" : "0.15"
      },
      {
         "OS" : "linux",
         "abstract" : "Generate fuzz and corpus-driven test harnesses",
         "dir" : "/home/runner/work/App-Test-Generator/App-Test-Generator",
         "finish" : 1762907629.89852,
         "name" : "App-Test-Generator",
         "perl" : "5.40.3",
         "run" : "t/eof.t",
         "start" : 1762907629.89823,
         "version" : "0.15"
      },
      {
         "OS" : "linux",
         "abstract" : "Generate fuzz and corpus-driven test harnesses",
         "dir" : "/home/runner/work/App-Test-Generator/App-Test-Generator",
         "finish" : 1762907630.14582,
         "name" : "App-Test-Generator",
         "perl" : "5.40.3",
         "run" : "t/eol.t",
         "start" : 1762907630.14555,
         "version" : "0.15"
      },
      {
         "OS" : "linux",
         "abstract" : "Generate fuzz and corpus-driven test harnesses",
         "dir" : "/home/runner/work/App-Test-Generator/App-Test-Generator",
         "finish" : 1762907630.52706,
         "name" : "App-Test-Generator",
         "perl" : "5.40.3",
         "run" : "t/errors.t",
         "start" : 1762907630.4841,
         "version" : "0.15"
      },
      {
         "OS" : "linux",
         "abstract" : "Generate fuzz and corpus-driven test harnesses",
         "dir" : "/home/runner/work/App-Test-Generator/App-Test-Generator",
         "finish" : 1762907630.9652,
         "name" : "App-Test-Generator",
         "perl" : "5.40.3",
         "run" : "t/fuzz.t",
         "start" : 1762907630.96486,
         "version" : "0.15"
      },
      {
         "OS" : "linux",
         "abstract" : "Generate fuzz and corpus-driven test harnesses",
         "dir" : "/home/runner/work/App-Test-Generator/App-Test-Generator",
         "finish" : 1762907631.21889,
         "name" : "App-Test-Generator",
         "perl" : "5.40.3",
         "run" : "t/generate.t",
         "start" : 1762907631.2186,
         "version" : "0.15"
      },
      {
         "OS" : "linux",
         "abstract" : "Generate fuzz and corpus-driven test harnesses",
         "dir" : "/home/runner/work/App-Test-Generator/App-Test-Generator",
         "finish" : 1762907631.4264,
         "name" : "App-Test-Generator",
         "perl" : "5.40.3",
         "run" : "t/html_genealogy_map.t",
         "start" : 1762907631.42632,
         "version" : "0.15"
      },
      {
         "OS" : "linux",
         "abstract" : "Generate fuzz and corpus-driven test harnesses",
         "dir" : "/home/runner/work/App-Test-Generator/App-Test-Generator",
         "finish" : 1762907631.65687,
         "name" : "App-Test-Generator",
         "perl" : "5.40.3",
         "run" : "t/pod-cm.t",
         "start" : 1762907631.65654,
         "version" : "0.15"
      },
      {
         "OS" : "linux",
         "abstract" : "Generate fuzz and corpus-driven test harnesses",
         "dir" : "/home/runner/work/App-Test-Generator/App-Test-Generator",
         "finish" : 1762907631.89868,
         "name" : "App-Test-Generator",
         "perl" : "5.40.3",
         "run" : "t/pod-coverage.t",
         "start" : 1762907631.89845,
         "version" : "0.15"
      },
      {
         "OS" : "linux",
         "abstract" : "Generate fuzz and corpus-driven test harnesses",
         "dir" : "/home/runner/work/App-Test-Generator/App-Test-Generator",
         "finish" : 1762907632.13848,
         "name" : "App-Test-Generator",
         "perl" : "5.40.3",
         "run" : "t/pod-spelling.t",
         "start" : 1762907632.13821,
         "version" : "0.15"
      },
      {
         "OS" : "linux",
         "abstract" : "Generate fuzz and corpus-driven test harnesses",
         "dir" : "/home/runner/work/App-Test-Generator/App-Test-Generator",
         "finish" : 1762907632.37961,
         "name" : "App-Test-Generator",
         "perl" : "5.40.3",
         "run" : "t/pod-synopsis.t",
         "start" : 1762907632.37933,
         "version" : "0.15"
      },
      {
         "OS" : "linux",
         "abstract" : "Generate fuzz and corpus-driven test harnesses",
         "dir" : "/home/runner/work/App-Test-Generator/App-Test-Generator",
         "finish" : 1762907632.62264,
         "name" : "App-Test-Generator",
         "perl" : "5.40.3",
         "run" : "t/pod.t",
         "start" : 1762907632.62235,
         "version" : "0.15"
      },
      {
         "OS" : "linux",
         "abstract" : "Generate fuzz and corpus-driven test harnesses",
         "dir" : "/home/runner/work/App-Test-Generator/App-Test-Generator",
         "finish" : 1762907632.86678,
         "name" : "App-Test-Generator",
         "perl" : "5.40.3",
         "run" : "t/unused.t",
         "start" : 1762907632.86651,
         "version" : "0.15"
      },
      {
         "OS" : "linux",
         "abstract" : "Generate fuzz and corpus-driven test harnesses",
         "dir" : "/home/runner/work/App-Test-Generator/App-Test-Generator",
         "finish" : 1762907633.11195,
         "name" : "App-Test-Generator",
         "perl" : "5.40.3",
         "run" : "t/vars.t",
         "start" : 1762907633.11165,
         "version" : "0.15"
      }
   ],
   "summary" : {
      "Total" : {
         "branch" : {
            "covered" : 138,
            "error" : 92,
            "percentage" : 60,
            "total" : 230,
            "uncoverable" : 0
         },
         "condition" : {
            "covered" : 58,
            "error" : 71,
            "percentage" : 44.9612403100775,
            "total" : 129,
            "uncoverable" : 0
         },
         "statement" : {
            "covered" : 288,
            "error" : 93,
            "percentage" : 75.5905511811024,
            "total" : 381
         },
         "subroutine" : {
            "covered" : 27,
            "error" : 1,
            "percentage" : 96.4285714285714,
            "total" : 28
         },
         "total" : {
            "covered" : 511,
            "error" : 257,
            "percentage" : 66.5364583333333,
            "total" : 768,
            "uncoverable" : 0
         }
      },
      "blib/lib/App/Test/Generator.pm" : {
         "branch" : {
            "covered" : 138,
            "error" : 92,
            "percentage" : 60,
            "total" : 230,
            "uncoverable" : 0
         },
         "condition" : {
            "covered" : 58,
            "error" : 71,
            "percentage" : 44.9612403100775,
            "total" : 129,
            "uncoverable" : 0
         },
         "statement" : {
            "covered" : 288,
            "error" : 93,
            "percentage" : 75.5905511811024,
            "total" : 381
         },
         "subroutine" : {
            "covered" : 27,
            "error" : 1,
            "percentage" : 96.4285714285714,
            "total" : 28
         },
         "total" : {
            "covered" : 511,
            "error" : 257,
            "percentage" : 66.5364583333333,
            "total" : 768,
            "uncoverable" : 0
         }
      }
   }
}
