{
   "runs" : [
      {
         "OS" : "linux",
         "abstract" : "Generate fuzz and corpus-driven test harnesses",
         "dir" : "/home/runner/work/App-Test-Generator/App-Test-Generator",
         "finish" : 1766062080.82603,
         "name" : "App-Test-Generator",
         "perl" : "5.40.3",
         "run" : "-e",
         "start" : 1766062080.82559,
         "version" : "0.21"
      },
      {
         "OS" : "linux",
         "abstract" : "Generate fuzz and corpus-driven test harnesses",
         "dir" : "/home/runner/work/App-Test-Generator/App-Test-Generator",
         "finish" : 1766062080.99575,
         "name" : "App-Test-Generator",
         "perl" : "5.40.3",
         "run" : "-e",
         "start" : 1766062080.9955,
         "version" : "0.21"
      },
      {
         "OS" : "linux",
         "abstract" : "Generate fuzz and corpus-driven test harnesses",
         "dir" : "/home/runner/work/App-Test-Generator/App-Test-Generator",
         "finish" : 1766062081.15997,
         "name" : "App-Test-Generator",
         "perl" : "5.40.3",
         "run" : "-e",
         "start" : 1766062081.15964,
         "version" : "0.21"
      },
      {
         "OS" : "linux",
         "abstract" : "Generate fuzz and corpus-driven test harnesses",
         "dir" : "/home/runner/work/App-Test-Generator/App-Test-Generator",
         "finish" : 1766062081.32176,
         "name" : "App-Test-Generator",
         "perl" : "5.40.3",
         "run" : "-e",
         "start" : 1766062081.32143,
         "version" : "0.21"
      },
      {
         "OS" : "linux",
         "abstract" : "Generate fuzz and corpus-driven test harnesses",
         "dir" : "/home/runner/work/App-Test-Generator/App-Test-Generator",
         "finish" : 1766062081.48464,
         "name" : "App-Test-Generator",
         "perl" : "5.40.3",
         "run" : "-e",
         "start" : 1766062081.48443,
         "version" : "0.21"
      },
      {
         "OS" : "linux",
         "abstract" : "Generate fuzz and corpus-driven test harnesses",
         "dir" : "/home/runner/work/App-Test-Generator/App-Test-Generator",
         "finish" : 1766062081.64985,
         "name" : "App-Test-Generator",
         "perl" : "5.40.3",
         "run" : "-e",
         "start" : 1766062081.64964,
         "version" : "0.21"
      },
      {
         "OS" : "linux",
         "abstract" : "Generate fuzz and corpus-driven test harnesses",
         "dir" : "/home/runner/work/App-Test-Generator/App-Test-Generator",
         "finish" : 1766062081.8122,
         "name" : "App-Test-Generator",
         "perl" : "5.40.3",
         "run" : "-e",
         "start" : 1766062081.812,
         "version" : "0.21"
      },
      {
         "OS" : "linux",
         "abstract" : "Generate fuzz and corpus-driven test harnesses",
         "dir" : "/home/runner/work/App-Test-Generator/App-Test-Generator",
         "finish" : 1766062081.97493,
         "name" : "App-Test-Generator",
         "perl" : "5.40.3",
         "run" : "-e",
         "start" : 1766062081.97473,
         "version" : "0.21"
      },
      {
         "OS" : "linux",
         "abstract" : "Generate fuzz and corpus-driven test harnesses",
         "dir" : "/home/runner/work/App-Test-Generator/App-Test-Generator",
         "finish" : 1766062082.17803,
         "name" : "App-Test-Generator",
         "perl" : "5.40.3",
         "run" : "-e",
         "start" : 1766062082.14488,
         "version" : "0.21"
      },
      {
         "OS" : "linux",
         "abstract" : "Generate fuzz and corpus-driven test harnesses",
         "dir" : "/home/runner/work/App-Test-Generator/App-Test-Generator",
         "finish" : 1766062082.39691,
         "name" : "App-Test-Generator",
         "perl" : "5.40.3",
         "run" : "-e",
         "start" : 1766062082.39647,
         "version" : "0.21"
      },
      {
         "OS" : "linux",
         "abstract" : "Generate fuzz and corpus-driven test harnesses",
         "dir" : "/home/runner/work/App-Test-Generator/App-Test-Generator",
         "finish" : 1766062082.61538,
         "name" : "App-Test-Generator",
         "perl" : "5.40.3",
         "run" : "-e",
         "start" : 1766062082.61496,
         "version" : "0.21"
      },
      {
         "OS" : "linux",
         "abstract" : "Generate fuzz and corpus-driven test harnesses",
         "dir" : "/home/runner/work/App-Test-Generator/App-Test-Generator",
         "finish" : 1766062092.86003,
         "name" : "App-Test-Generator",
         "perl" : "5.40.3",
         "run" : "-e",
         "start" : 1766062082.80765,
         "version" : "0.21"
      },
      {
         "OS" : "linux",
         "abstract" : "Generate fuzz and corpus-driven test harnesses",
         "dir" : "/home/runner/work/App-Test-Generator/App-Test-Generator",
         "finish" : 1766062082.9518,
         "name" : "App-Test-Generator",
         "perl" : "5.40.3",
         "run" : "-e",
         "start" : 1766062082.95172,
         "version" : "0.21"
      },
      {
         "OS" : "linux",
         "abstract" : "Generate fuzz and corpus-driven test harnesses",
         "dir" : "/home/runner/work/App-Test-Generator/App-Test-Generator",
         "finish" : 1766062083.26777,
         "name" : "App-Test-Generator",
         "perl" : "5.40.3",
         "run" : "t/10-compile.t",
         "start" : 1766062083.26688,
         "version" : "0.21"
      },
      {
         "OS" : "linux",
         "abstract" : "Generate fuzz and corpus-driven test harnesses",
         "dir" : "/home/runner/work/App-Test-Generator/App-Test-Generator",
         "finish" : 1766062083.88667,
         "name" : "App-Test-Generator",
         "perl" : "5.40.3",
         "run" : "t/30-basics.t",
         "start" : 1766062083.81573,
         "version" : "0.21"
      },
      {
         "OS" : "linux",
         "abstract" : "Generate fuzz and corpus-driven test harnesses",
         "dir" : "/home/runner/work/App-Test-Generator/App-Test-Generator",
         "finish" : 1766062084.62153,
         "name" : "App-Test-Generator",
         "perl" : "5.40.3",
         "run" : "t/40-more.t",
         "start" : 1766062084.45261,
         "version" : "0.21"
      },
      {
         "OS" : "linux",
         "abstract" : "Generate fuzz and corpus-driven test harnesses",
         "dir" : "/home/runner/work/App-Test-Generator/App-Test-Generator",
         "finish" : 1766062085.97501,
         "name" : "App-Test-Generator",
         "perl" : "5.40.3",
         "run" : "t/abs.t",
         "start" : 1766062085.20489,
         "version" : "0.21"
      },
      {
         "OS" : "linux",
         "abstract" : "Generate fuzz and corpus-driven test harnesses",
         "dir" : "/home/runner/work/App-Test-Generator/App-Test-Generator",
         "finish" : 1766062085.88477,
         "name" : "App-Test-Generator",
         "perl" : "5.40.3",
         "run" : "t/tmp_abs.t",
         "start" : 1766062085.77805,
         "version" : "0.21"
      },
      {
         "OS" : "linux",
         "abstract" : "Generate fuzz and corpus-driven test harnesses",
         "dir" : "/home/runner/work/App-Test-Generator/App-Test-Generator",
         "finish" : 1766062086.43939,
         "name" : "App-Test-Generator",
         "perl" : "5.40.3",
         "run" : "t/advanced_types.t",
         "start" : 1766062086.43912,
         "version" : "0.21"
      },
      {
         "OS" : "linux",
         "abstract" : "Generate fuzz and corpus-driven test harnesses",
         "dir" : "/home/runner/work/App-Test-Generator/App-Test-Generator",
         "finish" : 1766062086.76148,
         "name" : "App-Test-Generator",
         "perl" : "5.40.3",
         "run" : "t/conf-corpus.t",
         "start" : 1766062086.76116,
         "version" : "0.21"
      },
      {
         "OS" : "linux",
         "abstract" : "Generate fuzz and corpus-driven test harnesses",
         "dir" : "/home/runner/work/App-Test-Generator/App-Test-Generator",
         "finish" : 1766062087.24229,
         "name" : "App-Test-Generator",
         "perl" : "5.40.3",
         "run" : "t/conf-fuzz.t",
         "start" : 1766062087.242,
         "version" : "0.21"
      },
      {
         "OS" : "linux",
         "abstract" : "Generate fuzz and corpus-driven test harnesses",
         "dir" : "/home/runner/work/App-Test-Generator/App-Test-Generator",
         "finish" : 1766062087.88734,
         "name" : "App-Test-Generator",
         "perl" : "5.40.3",
         "run" : "t/default_value_extraction.t",
         "start" : 1766062087.65259,
         "version" : "0.21"
      },
      {
         "OS" : "linux",
         "abstract" : "Generate fuzz and corpus-driven test harnesses",
         "dir" : "/home/runner/work/App-Test-Generator/App-Test-Generator",
         "finish" : 1766062088.66339,
         "name" : "App-Test-Generator",
         "perl" : "5.40.3",
         "run" : "t/eof.t",
         "start" : 1766062088.66318,
         "version" : "0.21"
      },
      {
         "OS" : "linux",
         "abstract" : "Generate fuzz and corpus-driven test harnesses",
         "dir" : "/home/runner/work/App-Test-Generator/App-Test-Generator",
         "finish" : 1766062088.89763,
         "name" : "App-Test-Generator",
         "perl" : "5.40.3",
         "run" : "t/eol.t",
         "start" : 1766062088.89741,
         "version" : "0.21"
      },
      {
         "OS" : "linux",
         "abstract" : "Generate fuzz and corpus-driven test harnesses",
         "dir" : "/home/runner/work/App-Test-Generator/App-Test-Generator",
         "finish" : 1766062089.28545,
         "name" : "App-Test-Generator",
         "perl" : "5.40.3",
         "run" : "t/errors.t",
         "start" : 1766062089.23893,
         "version" : "0.21"
      },
      {
         "OS" : "linux",
         "abstract" : "Generate fuzz and corpus-driven test harnesses",
         "dir" : "/home/runner/work/App-Test-Generator/App-Test-Generator",
         "finish" : 1766062089.78511,
         "name" : "App-Test-Generator",
         "perl" : "5.40.3",
         "run" : "t/fuzz.t",
         "start" : 1766062089.78486,
         "version" : "0.21"
      },
      {
         "OS" : "linux",
         "abstract" : "Generate fuzz and corpus-driven test harnesses",
         "dir" : "/home/runner/work/App-Test-Generator/App-Test-Generator",
         "finish" : 1766062090.02995,
         "name" : "App-Test-Generator",
         "perl" : "5.40.3",
         "run" : "t/generate.t",
         "start" : 1766062090.02971,
         "version" : "0.21"
      },
      {
         "OS" : "linux",
         "abstract" : "Generate fuzz and corpus-driven test harnesses",
         "dir" : "/home/runner/work/App-Test-Generator/App-Test-Generator",
         "finish" : 1766062090.23716,
         "name" : "App-Test-Generator",
         "perl" : "5.40.3",
         "run" : "t/html_genealogy_map.t",
         "start" : 1766062090.23709,
         "version" : "0.21"
      },
      {
         "OS" : "linux",
         "abstract" : "Generate fuzz and corpus-driven test harnesses",
         "dir" : "/home/runner/work/App-Test-Generator/App-Test-Generator",
         "finish" : 1766062090.46342,
         "name" : "App-Test-Generator",
         "perl" : "5.40.3",
         "run" : "t/object_detection.t",
         "start" : 1766062090.46316,
         "version" : "0.21"
      },
      {
         "OS" : "linux",
         "abstract" : "Generate fuzz and corpus-driven test harnesses",
         "dir" : "/home/runner/work/App-Test-Generator/App-Test-Generator",
         "finish" : 1766062090.69844,
         "name" : "App-Test-Generator",
         "perl" : "5.40.3",
         "run" : "t/pod-cm.t",
         "start" : 1766062090.6982,
         "version" : "0.21"
      },
      {
         "OS" : "linux",
         "abstract" : "Generate fuzz and corpus-driven test harnesses",
         "dir" : "/home/runner/work/App-Test-Generator/App-Test-Generator",
         "finish" : 1766062090.94058,
         "name" : "App-Test-Generator",
         "perl" : "5.40.3",
         "run" : "t/pod-coverage.t",
         "start" : 1766062090.94036,
         "version" : "0.21"
      },
      {
         "OS" : "linux",
         "abstract" : "Generate fuzz and corpus-driven test harnesses",
         "dir" : "/home/runner/work/App-Test-Generator/App-Test-Generator",
         "finish" : 1766062091.1748,
         "name" : "App-Test-Generator",
         "perl" : "5.40.3",
         "run" : "t/pod-spelling.t",
         "start" : 1766062091.17456,
         "version" : "0.21"
      },
      {
         "OS" : "linux",
         "abstract" : "Generate fuzz and corpus-driven test harnesses",
         "dir" : "/home/runner/work/App-Test-Generator/App-Test-Generator",
         "finish" : 1766062091.40993,
         "name" : "App-Test-Generator",
         "perl" : "5.40.3",
         "run" : "t/pod-synopsis.t",
         "start" : 1766062091.40972,
         "version" : "0.21"
      },
      {
         "OS" : "linux",
         "abstract" : "Generate fuzz and corpus-driven test harnesses",
         "dir" : "/home/runner/work/App-Test-Generator/App-Test-Generator",
         "finish" : 1766062091.64451,
         "name" : "App-Test-Generator",
         "perl" : "5.40.3",
         "run" : "t/pod.t",
         "start" : 1766062091.6443,
         "version" : "0.21"
      },
      {
         "OS" : "linux",
         "abstract" : "Generate fuzz and corpus-driven test harnesses",
         "dir" : "/home/runner/work/App-Test-Generator/App-Test-Generator",
         "finish" : 1766062091.87912,
         "name" : "App-Test-Generator",
         "perl" : "5.40.3",
         "run" : "t/relationship_tests.t",
         "start" : 1766062091.87889,
         "version" : "0.21"
      },
      {
         "OS" : "linux",
         "abstract" : "Generate fuzz and corpus-driven test harnesses",
         "dir" : "/home/runner/work/App-Test-Generator/App-Test-Generator",
         "finish" : 1766062092.1141,
         "name" : "App-Test-Generator",
         "perl" : "5.40.3",
         "run" : "t/return.t",
         "start" : 1766062092.11387,
         "version" : "0.21"
      },
      {
         "OS" : "linux",
         "abstract" : "Generate fuzz and corpus-driven test harnesses",
         "dir" : "/home/runner/work/App-Test-Generator/App-Test-Generator",
         "finish" : 1766062092.34754,
         "name" : "App-Test-Generator",
         "perl" : "5.40.3",
         "run" : "t/test_extractor.t",
         "start" : 1766062092.34734,
         "version" : "0.21"
      },
      {
         "OS" : "linux",
         "abstract" : "Generate fuzz and corpus-driven test harnesses",
         "dir" : "/home/runner/work/App-Test-Generator/App-Test-Generator",
         "finish" : 1766062092.58137,
         "name" : "App-Test-Generator",
         "perl" : "5.40.3",
         "run" : "t/unused.t",
         "start" : 1766062092.58116,
         "version" : "0.21"
      },
      {
         "OS" : "linux",
         "abstract" : "Generate fuzz and corpus-driven test harnesses",
         "dir" : "/home/runner/work/App-Test-Generator/App-Test-Generator",
         "finish" : 1766062092.81694,
         "name" : "App-Test-Generator",
         "perl" : "5.40.3",
         "run" : "t/vars.t",
         "start" : 1766062092.81664,
         "version" : "0.21"
      }
   ],
   "summary" : {
      "Total" : {
         "branch" : {
            "covered" : 605,
            "error" : 897,
            "percentage" : 40.2796271637816,
            "total" : 1502,
            "uncoverable" : 0
         },
         "condition" : {
            "covered" : 217,
            "error" : 504,
            "percentage" : 30.0970873786408,
            "total" : 721,
            "uncoverable" : 0
         },
         "statement" : {
            "covered" : 1317,
            "error" : 1083,
            "percentage" : 54.875,
            "total" : 2400
         },
         "subroutine" : {
            "covered" : 117,
            "error" : 24,
            "percentage" : 82.9787234042553,
            "total" : 141
         },
         "total" : {
            "covered" : 2256,
            "error" : 2508,
            "percentage" : 47.3551637279597,
            "total" : 4764,
            "uncoverable" : 0
         }
      },
      "blib/lib/App/Test/Generator.pm" : {
         "branch" : {
            "covered" : 174,
            "error" : 174,
            "percentage" : 50,
            "total" : 348,
            "uncoverable" : 0
         },
         "condition" : {
            "covered" : 83,
            "error" : 123,
            "percentage" : 40.2912621359223,
            "total" : 206,
            "uncoverable" : 0
         },
         "statement" : {
            "covered" : 427,
            "error" : 223,
            "percentage" : 65.6923076923077,
            "total" : 650
         },
         "subroutine" : {
            "covered" : 42,
            "error" : 14,
            "percentage" : 75,
            "total" : 56
         },
         "total" : {
            "covered" : 726,
            "error" : 534,
            "percentage" : 57.6190476190476,
            "total" : 1260,
            "uncoverable" : 0
         }
      },
      "blib/lib/App/Test/Generator/SchemaExtractor.pm" : {
         "branch" : {
            "covered" : 430,
            "error" : 722,
            "percentage" : 37.3263888888889,
            "total" : 1152,
            "uncoverable" : 0
         },
         "condition" : {
            "covered" : 133,
            "error" : 379,
            "percentage" : 25.9765625,
            "total" : 512,
            "uncoverable" : 0
         },
         "statement" : {
            "covered" : 872,
            "error" : 860,
            "percentage" : 50.3464203233256,
            "total" : 1732
         },
         "subroutine" : {
            "covered" : 69,
            "error" : 10,
            "percentage" : 87.3417721518987,
            "total" : 79
         },
         "total" : {
            "covered" : 1504,
            "error" : 1971,
            "percentage" : 43.2805755395683,
            "total" : 3475,
            "uncoverable" : 0
         }
      },
      "blib/lib/App/Test/Generator/Template.pm" : {
         "branch" : {
            "covered" : 1,
            "error" : 1,
            "percentage" : 50,
            "total" : 2,
            "uncoverable" : 0
         },
         "condition" : {
            "covered" : 1,
            "error" : 2,
            "percentage" : 33.3333333333333,
            "total" : 3,
            "uncoverable" : 0
         },
         "statement" : {
            "covered" : 18,
            "percentage" : 100,
            "total" : 18
         },
         "subroutine" : {
            "covered" : 6,
            "percentage" : 100,
            "total" : 6
         },
         "total" : {
            "covered" : 26,
            "error" : 3,
            "percentage" : 89.6551724137931,
            "total" : 29,
            "uncoverable" : 0
         }
      }
   }
}
