{
   "runs" : [
      {
         "OS" : "linux",
         "abstract" : "Generate fuzz and corpus-driven test harnesses from test schemas",
         "dir" : "/home/runner/work/App-Test-Generator/App-Test-Generator",
         "finish" : 1775475643.85827,
         "name" : "App-Test-Generator",
         "perl" : "5.40.4",
         "run" : "-e",
         "start" : 1775475624.25312,
         "version" : "0.30"
      },
      {
         "OS" : "linux",
         "abstract" : "Generate fuzz and corpus-driven test harnesses from test schemas",
         "dir" : "/home/runner/work/App-Test-Generator/App-Test-Generator",
         "finish" : 1775475624.40217,
         "name" : "App-Test-Generator",
         "perl" : "5.40.4",
         "run" : "-e",
         "start" : 1775475624.40204,
         "version" : "0.30"
      },
      {
         "OS" : "linux",
         "abstract" : "Generate fuzz and corpus-driven test harnesses from test schemas",
         "dir" : "/home/runner/work/App-Test-Generator/App-Test-Generator",
         "finish" : 1775475624.73578,
         "name" : "App-Test-Generator",
         "perl" : "5.40.4",
         "run" : "t/10-compile.t",
         "start" : 1775475624.73489,
         "version" : "0.30"
      },
      {
         "OS" : "linux",
         "abstract" : "Generate fuzz and corpus-driven test harnesses from test schemas",
         "dir" : "/home/runner/work/App-Test-Generator/App-Test-Generator",
         "finish" : 1775475625.41365,
         "name" : "App-Test-Generator",
         "perl" : "5.40.4",
         "run" : "t/30-basics.t",
         "start" : 1775475625.32493,
         "version" : "0.30"
      },
      {
         "OS" : "linux",
         "abstract" : "Generate fuzz and corpus-driven test harnesses from test schemas",
         "dir" : "/home/runner/work/App-Test-Generator/App-Test-Generator",
         "finish" : 1775475626.25563,
         "name" : "App-Test-Generator",
         "perl" : "5.40.4",
         "run" : "t/40-more.t",
         "start" : 1775475626.03047,
         "version" : "0.30"
      },
      {
         "OS" : "linux",
         "abstract" : "Generate fuzz and corpus-driven test harnesses from test schemas",
         "dir" : "/home/runner/work/App-Test-Generator/App-Test-Generator",
         "finish" : 1775475628.59949,
         "name" : "App-Test-Generator",
         "perl" : "5.40.4",
         "run" : "t/abs.t",
         "start" : 1775475626.8134,
         "version" : "0.30"
      },
      {
         "OS" : "linux",
         "abstract" : "Generate fuzz and corpus-driven test harnesses from test schemas",
         "dir" : "/home/runner/work/App-Test-Generator/App-Test-Generator",
         "finish" : 1775475628.48847,
         "name" : "App-Test-Generator",
         "perl" : "5.40.4",
         "run" : "t/tmp_abs.t",
         "start" : 1775475627.47422,
         "version" : "0.30"
      },
      {
         "OS" : "linux",
         "abstract" : "Generate fuzz and corpus-driven test harnesses from test schemas",
         "dir" : "/home/runner/work/App-Test-Generator/App-Test-Generator",
         "finish" : 1775475629.11167,
         "name" : "App-Test-Generator",
         "perl" : "5.40.4",
         "run" : "t/advanced_types.t",
         "start" : 1775475629.11139,
         "version" : "0.30"
      },
      {
         "OS" : "linux",
         "abstract" : "Generate fuzz and corpus-driven test harnesses from test schemas",
         "dir" : "/home/runner/work/App-Test-Generator/App-Test-Generator",
         "finish" : 1775475629.35055,
         "name" : "App-Test-Generator",
         "perl" : "5.40.4",
         "run" : "t/cli-extract-schemas.t",
         "start" : 1775475629.35027,
         "version" : "0.30"
      },
      {
         "OS" : "linux",
         "abstract" : "Generate fuzz and corpus-driven test harnesses from test schemas",
         "dir" : "/home/runner/work/App-Test-Generator/App-Test-Generator",
         "finish" : 1775475633.3339,
         "name" : "App-Test-Generator",
         "perl" : "5.40.4",
         "run" : "t/cli-fuzz-harness-generator.t",
         "start" : 1775475629.62436,
         "version" : "0.30"
      },
      {
         "OS" : "linux",
         "abstract" : "Generate fuzz and corpus-driven test harnesses from test schemas",
         "dir" : "/home/runner/work/App-Test-Generator/App-Test-Generator",
         "finish" : 1775475629.91764,
         "name" : "App-Test-Generator",
         "perl" : "5.40.4",
         "run" : "/home/runner/work/App-Test-Generator/App-Test-Generator/t/../bin/fuzz-harness-generator",
         "start" : 1775475629.89988,
         "version" : "0.30"
      },
      {
         "OS" : "linux",
         "abstract" : "Generate fuzz and corpus-driven test harnesses from test schemas",
         "dir" : "/home/runner/work/App-Test-Generator/App-Test-Generator",
         "finish" : 1775475630.50411,
         "name" : "App-Test-Generator",
         "perl" : "5.40.4",
         "run" : "/home/runner/work/App-Test-Generator/App-Test-Generator/t/../bin/fuzz-harness-generator",
         "start" : 1775475630.50347,
         "version" : "0.30"
      },
      {
         "OS" : "linux",
         "abstract" : "Generate fuzz and corpus-driven test harnesses from test schemas",
         "dir" : "/home/runner/work/App-Test-Generator/App-Test-Generator",
         "finish" : 1775475631.14641,
         "name" : "App-Test-Generator",
         "perl" : "5.40.4",
         "run" : "/home/runner/work/App-Test-Generator/App-Test-Generator/t/../bin/fuzz-harness-generator",
         "start" : 1775475631.09964,
         "version" : "0.30"
      },
      {
         "OS" : "linux",
         "abstract" : "Generate fuzz and corpus-driven test harnesses from test schemas",
         "dir" : "/home/runner/work/App-Test-Generator/App-Test-Generator",
         "finish" : 1775475631.78656,
         "name" : "App-Test-Generator",
         "perl" : "5.40.4",
         "run" : "/home/runner/work/App-Test-Generator/App-Test-Generator/t/../bin/fuzz-harness-generator",
         "start" : 1775475631.73298,
         "version" : "0.30"
      },
      {
         "OS" : "linux",
         "abstract" : "Generate fuzz and corpus-driven test harnesses from test schemas",
         "dir" : "/home/runner/work/App-Test-Generator/App-Test-Generator",
         "finish" : 1775475632.42913,
         "name" : "App-Test-Generator",
         "perl" : "5.40.4",
         "run" : "/home/runner/work/App-Test-Generator/App-Test-Generator/t/../bin/fuzz-harness-generator",
         "start" : 1775475632.38547,
         "version" : "0.30"
      },
      {
         "OS" : "linux",
         "abstract" : "Generate fuzz and corpus-driven test harnesses from test schemas",
         "dir" : "/home/runner/work/App-Test-Generator/App-Test-Generator",
         "finish" : 1775475633.02152,
         "name" : "App-Test-Generator",
         "perl" : "5.40.4",
         "run" : "/home/runner/work/App-Test-Generator/App-Test-Generator/t/../bin/fuzz-harness-generator",
         "start" : 1775475633.01949,
         "version" : "0.30"
      },
      {
         "OS" : "linux",
         "abstract" : "Generate fuzz and corpus-driven test harnesses from test schemas",
         "dir" : "/home/runner/work/App-Test-Generator/App-Test-Generator",
         "finish" : 1775475633.68494,
         "name" : "App-Test-Generator",
         "perl" : "5.40.4",
         "run" : "t/conf-corpus.t",
         "start" : 1775475633.68463,
         "version" : "0.30"
      },
      {
         "OS" : "linux",
         "abstract" : "Generate fuzz and corpus-driven test harnesses from test schemas",
         "dir" : "/home/runner/work/App-Test-Generator/App-Test-Generator",
         "finish" : 1775475634.21388,
         "name" : "App-Test-Generator",
         "perl" : "5.40.4",
         "run" : "t/conf-fuzz.t",
         "start" : 1775475634.21356,
         "version" : "0.30"
      },
      {
         "OS" : "linux",
         "abstract" : "Generate fuzz and corpus-driven test harnesses from test schemas",
         "dir" : "/home/runner/work/App-Test-Generator/App-Test-Generator",
         "finish" : 1775475634.46163,
         "name" : "App-Test-Generator",
         "perl" : "5.40.4",
         "run" : "t/default_value_extraction.t",
         "start" : 1775475634.46136,
         "version" : "0.30"
      },
      {
         "OS" : "linux",
         "abstract" : "Generate fuzz and corpus-driven test harnesses from test schemas",
         "dir" : "/home/runner/work/App-Test-Generator/App-Test-Generator",
         "finish" : 1775475634.70269,
         "name" : "App-Test-Generator",
         "perl" : "5.40.4",
         "run" : "t/dist.t",
         "start" : 1775475634.70243,
         "version" : "0.30"
      },
      {
         "OS" : "linux",
         "abstract" : "Generate fuzz and corpus-driven test harnesses from test schemas",
         "dir" : "/home/runner/work/App-Test-Generator/App-Test-Generator",
         "finish" : 1775475634.9403,
         "name" : "App-Test-Generator",
         "perl" : "5.40.4",
         "run" : "t/eof.t",
         "start" : 1775475634.94001,
         "version" : "0.30"
      },
      {
         "OS" : "linux",
         "abstract" : "Generate fuzz and corpus-driven test harnesses from test schemas",
         "dir" : "/home/runner/work/App-Test-Generator/App-Test-Generator",
         "finish" : 1775475635.18031,
         "name" : "App-Test-Generator",
         "perl" : "5.40.4",
         "run" : "t/eol.t",
         "start" : 1775475635.17999,
         "version" : "0.30"
      },
      {
         "OS" : "linux",
         "abstract" : "Generate fuzz and corpus-driven test harnesses from test schemas",
         "dir" : "/home/runner/work/App-Test-Generator/App-Test-Generator",
         "finish" : 1775475635.42086,
         "name" : "App-Test-Generator",
         "perl" : "5.40.4",
         "run" : "t/error_constraints.t",
         "start" : 1775475635.42058,
         "version" : "0.30"
      },
      {
         "OS" : "linux",
         "abstract" : "Generate fuzz and corpus-driven test harnesses from test schemas",
         "dir" : "/home/runner/work/App-Test-Generator/App-Test-Generator",
         "finish" : 1775475635.86644,
         "name" : "App-Test-Generator",
         "perl" : "5.40.4",
         "run" : "t/errors.t",
         "start" : 1775475635.77148,
         "version" : "0.30"
      },
      {
         "OS" : "linux",
         "abstract" : "Generate fuzz and corpus-driven test harnesses from test schemas",
         "dir" : "/home/runner/work/App-Test-Generator/App-Test-Generator",
         "finish" : 1775475636.42526,
         "name" : "App-Test-Generator",
         "perl" : "5.40.4",
         "run" : "t/fuzz.t",
         "start" : 1775475636.42491,
         "version" : "0.30"
      },
      {
         "OS" : "linux",
         "abstract" : "Generate fuzz and corpus-driven test harnesses from test schemas",
         "dir" : "/home/runner/work/App-Test-Generator/App-Test-Generator",
         "finish" : 1775475636.6741,
         "name" : "App-Test-Generator",
         "perl" : "5.40.4",
         "run" : "t/generate.t",
         "start" : 1775475636.67384,
         "version" : "0.30"
      },
      {
         "OS" : "linux",
         "abstract" : "Generate fuzz and corpus-driven test harnesses from test schemas",
         "dir" : "/home/runner/work/App-Test-Generator/App-Test-Generator",
         "finish" : 1775475637.02293,
         "name" : "App-Test-Generator",
         "perl" : "5.40.4",
         "run" : "t/generator-regression.t",
         "start" : 1775475636.95152,
         "version" : "0.30"
      },
      {
         "OS" : "linux",
         "abstract" : "Generate fuzz and corpus-driven test harnesses from test schemas",
         "dir" : "/home/runner/work/App-Test-Generator/App-Test-Generator",
         "finish" : 1775475637.52982,
         "name" : "App-Test-Generator",
         "perl" : "5.40.4",
         "run" : "t/getset_accessor.t",
         "start" : 1775475637.52955,
         "version" : "0.30"
      },
      {
         "OS" : "linux",
         "abstract" : "Generate fuzz and corpus-driven test harnesses from test schemas",
         "dir" : "/home/runner/work/App-Test-Generator/App-Test-Generator",
         "finish" : 1775475637.73792,
         "name" : "App-Test-Generator",
         "perl" : "5.40.4",
         "run" : "t/html_genealogy_map.t",
         "start" : 1775475637.73784,
         "version" : "0.30"
      },
      {
         "OS" : "linux",
         "abstract" : "Generate fuzz and corpus-driven test harnesses from test schemas",
         "dir" : "/home/runner/work/App-Test-Generator/App-Test-Generator",
         "finish" : 1775475638.05313,
         "name" : "App-Test-Generator",
         "perl" : "5.40.4",
         "run" : "t/instantiation.t",
         "start" : 1775475638.05285,
         "version" : "0.30"
      },
      {
         "OS" : "linux",
         "abstract" : "Generate fuzz and corpus-driven test harnesses from test schemas",
         "dir" : "/home/runner/work/App-Test-Generator/App-Test-Generator",
         "finish" : 1775475638.31606,
         "name" : "App-Test-Generator",
         "perl" : "5.40.4",
         "run" : "t/modern.t",
         "start" : 1775475638.3158,
         "version" : "0.30"
      },
      {
         "OS" : "linux",
         "abstract" : "Generate fuzz and corpus-driven test harnesses from test schemas",
         "dir" : "/home/runner/work/App-Test-Generator/App-Test-Generator",
         "finish" : 1775475638.5556,
         "name" : "App-Test-Generator",
         "perl" : "5.40.4",
         "run" : "t/moosex_params_validate.t",
         "start" : 1775475638.55532,
         "version" : "0.30"
      },
      {
         "OS" : "linux",
         "abstract" : "Generate fuzz and corpus-driven test harnesses from test schemas",
         "dir" : "/home/runner/work/App-Test-Generator/App-Test-Generator",
         "finish" : 1775475638.92848,
         "name" : "App-Test-Generator",
         "perl" : "5.40.4",
         "run" : "t/mutator.t",
         "start" : 1775475638.91661,
         "version" : "0.30"
      },
      {
         "OS" : "linux",
         "abstract" : "Generate fuzz and corpus-driven test harnesses from test schemas",
         "dir" : "/home/runner/work/App-Test-Generator/App-Test-Generator",
         "finish" : 1775475639.38767,
         "name" : "App-Test-Generator",
         "perl" : "5.40.4",
         "run" : "t/mutator_num_boundary.t",
         "start" : 1775475639.36891,
         "version" : "0.30"
      },
      {
         "OS" : "linux",
         "abstract" : "Generate fuzz and corpus-driven test harnesses from test schemas",
         "dir" : "/home/runner/work/App-Test-Generator/App-Test-Generator",
         "finish" : 1775475639.67205,
         "name" : "App-Test-Generator",
         "perl" : "5.40.4",
         "run" : "t/object_detection.t",
         "start" : 1775475639.67179,
         "version" : "0.30"
      },
      {
         "OS" : "linux",
         "abstract" : "Generate fuzz and corpus-driven test harnesses from test schemas",
         "dir" : "/home/runner/work/App-Test-Generator/App-Test-Generator",
         "finish" : 1775475639.915,
         "name" : "App-Test-Generator",
         "perl" : "5.40.4",
         "run" : "t/params_validate.t",
         "start" : 1775475639.91471,
         "version" : "0.30"
      },
      {
         "OS" : "linux",
         "abstract" : "Generate fuzz and corpus-driven test harnesses from test schemas",
         "dir" : "/home/runner/work/App-Test-Generator/App-Test-Generator",
         "finish" : 1775475640.16346,
         "name" : "App-Test-Generator",
         "perl" : "5.40.4",
         "run" : "t/params_validate_strict.t",
         "start" : 1775475640.16314,
         "version" : "0.30"
      },
      {
         "OS" : "linux",
         "abstract" : "Generate fuzz and corpus-driven test harnesses from test schemas",
         "dir" : "/home/runner/work/App-Test-Generator/App-Test-Generator",
         "finish" : 1775475640.40429,
         "name" : "App-Test-Generator",
         "perl" : "5.40.4",
         "run" : "t/pod-cm.t",
         "start" : 1775475640.40399,
         "version" : "0.30"
      },
      {
         "OS" : "linux",
         "abstract" : "Generate fuzz and corpus-driven test harnesses from test schemas",
         "dir" : "/home/runner/work/App-Test-Generator/App-Test-Generator",
         "finish" : 1775475640.6456,
         "name" : "App-Test-Generator",
         "perl" : "5.40.4",
         "run" : "t/pod-coverage.t",
         "start" : 1775475640.64534,
         "version" : "0.30"
      },
      {
         "OS" : "linux",
         "abstract" : "Generate fuzz and corpus-driven test harnesses from test schemas",
         "dir" : "/home/runner/work/App-Test-Generator/App-Test-Generator",
         "finish" : 1775475640.88459,
         "name" : "App-Test-Generator",
         "perl" : "5.40.4",
         "run" : "t/pod-spelling.t",
         "start" : 1775475640.88434,
         "version" : "0.30"
      },
      {
         "OS" : "linux",
         "abstract" : "Generate fuzz and corpus-driven test harnesses from test schemas",
         "dir" : "/home/runner/work/App-Test-Generator/App-Test-Generator",
         "finish" : 1775475641.1319,
         "name" : "App-Test-Generator",
         "perl" : "5.40.4",
         "run" : "t/pod-synopsis.t",
         "start" : 1775475641.1316,
         "version" : "0.30"
      },
      {
         "OS" : "linux",
         "abstract" : "Generate fuzz and corpus-driven test harnesses from test schemas",
         "dir" : "/home/runner/work/App-Test-Generator/App-Test-Generator",
         "finish" : 1775475641.37534,
         "name" : "App-Test-Generator",
         "perl" : "5.40.4",
         "run" : "t/pod.t",
         "start" : 1775475641.37506,
         "version" : "0.30"
      },
      {
         "OS" : "linux",
         "abstract" : "Generate fuzz and corpus-driven test harnesses from test schemas",
         "dir" : "/home/runner/work/App-Test-Generator/App-Test-Generator",
         "finish" : 1775475641.61786,
         "name" : "App-Test-Generator",
         "perl" : "5.40.4",
         "run" : "t/relationship_tests.t",
         "start" : 1775475641.6176,
         "version" : "0.30"
      },
      {
         "OS" : "linux",
         "abstract" : "Generate fuzz and corpus-driven test harnesses from test schemas",
         "dir" : "/home/runner/work/App-Test-Generator/App-Test-Generator",
         "finish" : 1775475641.8568,
         "name" : "App-Test-Generator",
         "perl" : "5.40.4",
         "run" : "t/return.t",
         "start" : 1775475641.85656,
         "version" : "0.30"
      },
      {
         "OS" : "linux",
         "abstract" : "Generate fuzz and corpus-driven test harnesses from test schemas",
         "dir" : "/home/runner/work/App-Test-Generator/App-Test-Generator",
         "finish" : 1775475642.10786,
         "name" : "App-Test-Generator",
         "perl" : "5.40.4",
         "run" : "t/schema_input.t",
         "start" : 1775475642.10756,
         "version" : "0.30"
      },
      {
         "OS" : "linux",
         "abstract" : "Generate fuzz and corpus-driven test harnesses from test schemas",
         "dir" : "/home/runner/work/App-Test-Generator/App-Test-Generator",
         "finish" : 1775475642.35076,
         "name" : "App-Test-Generator",
         "perl" : "5.40.4",
         "run" : "t/strict_pod.t",
         "start" : 1775475642.35047,
         "version" : "0.30"
      },
      {
         "OS" : "linux",
         "abstract" : "Generate fuzz and corpus-driven test harnesses from test schemas",
         "dir" : "/home/runner/work/App-Test-Generator/App-Test-Generator",
         "finish" : 1775475642.59268,
         "name" : "App-Test-Generator",
         "perl" : "5.40.4",
         "run" : "t/test_extractor.t",
         "start" : 1775475642.5924,
         "version" : "0.30"
      },
      {
         "OS" : "linux",
         "abstract" : "Generate fuzz and corpus-driven test harnesses from test schemas",
         "dir" : "/home/runner/work/App-Test-Generator/App-Test-Generator",
         "finish" : 1775475642.84277,
         "name" : "App-Test-Generator",
         "perl" : "5.40.4",
         "run" : "t/test_hints.t",
         "start" : 1775475642.84249,
         "version" : "0.30"
      },
      {
         "OS" : "linux",
         "abstract" : "Generate fuzz and corpus-driven test harnesses from test schemas",
         "dir" : "/home/runner/work/App-Test-Generator/App-Test-Generator",
         "finish" : 1775475643.0868,
         "name" : "App-Test-Generator",
         "perl" : "5.40.4",
         "run" : "t/type_params.t",
         "start" : 1775475643.08651,
         "version" : "0.30"
      },
      {
         "OS" : "linux",
         "abstract" : "Generate fuzz and corpus-driven test harnesses from test schemas",
         "dir" : "/home/runner/work/App-Test-Generator/App-Test-Generator",
         "finish" : 1775475643.3274,
         "name" : "App-Test-Generator",
         "perl" : "5.40.4",
         "run" : "t/unused.t",
         "start" : 1775475643.3271,
         "version" : "0.30"
      },
      {
         "OS" : "linux",
         "abstract" : "Generate fuzz and corpus-driven test harnesses from test schemas",
         "dir" : "/home/runner/work/App-Test-Generator/App-Test-Generator",
         "finish" : 1775475643.57059,
         "name" : "App-Test-Generator",
         "perl" : "5.40.4",
         "run" : "t/valid_inputs.t",
         "start" : 1775475643.57033,
         "version" : "0.30"
      },
      {
         "OS" : "linux",
         "abstract" : "Generate fuzz and corpus-driven test harnesses from test schemas",
         "dir" : "/home/runner/work/App-Test-Generator/App-Test-Generator",
         "finish" : 1775475643.8127,
         "name" : "App-Test-Generator",
         "perl" : "5.40.4",
         "run" : "t/vars.t",
         "start" : 1775475643.81243,
         "version" : "0.30"
      }
   ],
   "summary" : {
      "Total" : {
         "branch" : {
            "covered" : 261,
            "error" : 353,
            "percentage" : 42.5081433224756,
            "total" : 614,
            "uncoverable" : 0
         },
         "condition" : {
            "covered" : 114,
            "error" : 183,
            "percentage" : 38.3838383838384,
            "total" : 297,
            "uncoverable" : 0
         },
         "statement" : {
            "covered" : 756,
            "error" : 450,
            "percentage" : 62.6865671641791,
            "total" : 1206
         },
         "subroutine" : {
            "covered" : 109,
            "error" : 35,
            "percentage" : 75.6944444444444,
            "total" : 144
         },
         "total" : {
            "covered" : 1240,
            "error" : 1021,
            "percentage" : 54.84298982751,
            "total" : 2261,
            "uncoverable" : 0
         }
      },
      "bin/fuzz-harness-generator" : {
         "branch" : {
            "covered" : 21,
            "error" : 51,
            "percentage" : 29.1666666666667,
            "total" : 72,
            "uncoverable" : 0
         },
         "condition" : {
            "covered" : 10,
            "error" : 20,
            "percentage" : 33.3333333333333,
            "total" : 30,
            "uncoverable" : 0
         },
         "statement" : {
            "covered" : 57,
            "error" : 96,
            "percentage" : 37.2549019607843,
            "total" : 153
         },
         "subroutine" : {
            "covered" : 7,
            "error" : 4,
            "percentage" : 63.6363636363636,
            "total" : 11
         },
         "total" : {
            "covered" : 95,
            "error" : 171,
            "percentage" : 35.7142857142857,
            "total" : 266,
            "uncoverable" : 0
         }
      },
      "blib/lib/App/Test/Generator.pm" : {
         "branch" : {
            "covered" : 228,
            "error" : 244,
            "percentage" : 48.3050847457627,
            "total" : 472,
            "uncoverable" : 0
         },
         "condition" : {
            "covered" : 94,
            "error" : 132,
            "percentage" : 41.5929203539823,
            "total" : 226,
            "uncoverable" : 0
         },
         "statement" : {
            "covered" : 513,
            "error" : 271,
            "percentage" : 65.4336734693878,
            "total" : 784
         },
         "subroutine" : {
            "covered" : 49,
            "error" : 14,
            "percentage" : 77.7777777777778,
            "total" : 63
         },
         "total" : {
            "covered" : 884,
            "error" : 661,
            "percentage" : 57.2168284789644,
            "total" : 1545,
            "uncoverable" : 0
         }
      },
      "blib/lib/App/Test/Generator/Mutant.pm" : {
         "branch" : {
            "covered" : 1,
            "error" : 1,
            "percentage" : 50,
            "total" : 2,
            "uncoverable" : 0
         },
         "statement" : {
            "covered" : 12,
            "error" : 3,
            "percentage" : 80,
            "total" : 15
         },
         "subroutine" : {
            "covered" : 5,
            "error" : 3,
            "percentage" : 62.5,
            "total" : 8
         },
         "total" : {
            "covered" : 18,
            "error" : 7,
            "percentage" : 72,
            "total" : 25,
            "uncoverable" : 0
         }
      },
      "blib/lib/App/Test/Generator/Mutation/Base.pm" : {
         "statement" : {
            "covered" : 7,
            "error" : 2,
            "percentage" : 77.7777777777778,
            "total" : 9
         },
         "subroutine" : {
            "covered" : 3,
            "error" : 2,
            "percentage" : 60,
            "total" : 5
         },
         "total" : {
            "covered" : 10,
            "error" : 4,
            "percentage" : 71.4285714285714,
            "total" : 14
         }
      },
      "blib/lib/App/Test/Generator/Mutation/BooleanNegation.pm" : {
         "branch" : {
            "covered" : 0,
            "error" : 4,
            "percentage" : 0,
            "total" : 4,
            "uncoverable" : 0
         },
         "condition" : {
            "covered" : 1,
            "error" : 1,
            "percentage" : 50,
            "total" : 2,
            "uncoverable" : 0
         },
         "statement" : {
            "covered" : 20,
            "error" : 9,
            "percentage" : 68.9655172413793,
            "total" : 29
         },
         "subroutine" : {
            "covered" : 6,
            "error" : 2,
            "percentage" : 75,
            "total" : 8
         },
         "total" : {
            "covered" : 27,
            "error" : 16,
            "percentage" : 62.7906976744186,
            "total" : 43,
            "uncoverable" : 0
         }
      },
      "blib/lib/App/Test/Generator/Mutation/ConditionalInversion.pm" : {
         "branch" : {
            "covered" : 2,
            "error" : 12,
            "percentage" : 14.2857142857143,
            "total" : 14,
            "uncoverable" : 0
         },
         "condition" : {
            "covered" : 3,
            "error" : 10,
            "percentage" : 23.0769230769231,
            "total" : 13,
            "uncoverable" : 0
         },
         "statement" : {
            "covered" : 25,
            "error" : 17,
            "percentage" : 59.5238095238095,
            "total" : 42
         },
         "subroutine" : {
            "covered" : 6,
            "error" : 2,
            "percentage" : 75,
            "total" : 8
         },
         "total" : {
            "covered" : 36,
            "error" : 41,
            "percentage" : 46.7532467532468,
            "total" : 77,
            "uncoverable" : 0
         }
      },
      "blib/lib/App/Test/Generator/Mutation/NumericBoundary.pm" : {
         "branch" : {
            "covered" : 5,
            "error" : 3,
            "percentage" : 62.5,
            "total" : 8,
            "uncoverable" : 0
         },
         "condition" : {
            "covered" : 2,
            "error" : 2,
            "percentage" : 50,
            "total" : 4,
            "uncoverable" : 0
         },
         "statement" : {
            "covered" : 36,
            "percentage" : 100,
            "total" : 36
         },
         "subroutine" : {
            "covered" : 7,
            "percentage" : 100,
            "total" : 7
         },
         "total" : {
            "covered" : 50,
            "error" : 5,
            "percentage" : 90.9090909090909,
            "total" : 55,
            "uncoverable" : 0
         }
      },
      "blib/lib/App/Test/Generator/Mutation/ReturnUndef.pm" : {
         "branch" : {
            "covered" : 0,
            "error" : 2,
            "percentage" : 0,
            "total" : 2,
            "uncoverable" : 0
         },
         "condition" : {
            "covered" : 1,
            "error" : 1,
            "percentage" : 50,
            "total" : 2,
            "uncoverable" : 0
         },
         "statement" : {
            "covered" : 20,
            "error" : 8,
            "percentage" : 71.4285714285714,
            "total" : 28
         },
         "subroutine" : {
            "covered" : 6,
            "error" : 2,
            "percentage" : 75,
            "total" : 8
         },
         "total" : {
            "covered" : 27,
            "error" : 13,
            "percentage" : 67.5,
            "total" : 40,
            "uncoverable" : 0
         }
      },
      "blib/lib/App/Test/Generator/Mutator.pm" : {
         "branch" : {
            "covered" : 3,
            "error" : 35,
            "percentage" : 7.89473684210526,
            "total" : 38,
            "uncoverable" : 0
         },
         "condition" : {
            "covered" : 2,
            "error" : 15,
            "percentage" : 11.7647058823529,
            "total" : 17,
            "uncoverable" : 0
         },
         "statement" : {
            "covered" : 48,
            "error" : 44,
            "percentage" : 52.1739130434783,
            "total" : 92
         },
         "subroutine" : {
            "covered" : 14,
            "error" : 6,
            "percentage" : 70,
            "total" : 20
         },
         "total" : {
            "covered" : 67,
            "error" : 100,
            "percentage" : 40.1197604790419,
            "total" : 167,
            "uncoverable" : 0
         }
      },
      "blib/lib/App/Test/Generator/Template.pm" : {
         "branch" : {
            "covered" : 1,
            "error" : 1,
            "percentage" : 50,
            "total" : 2,
            "uncoverable" : 0
         },
         "condition" : {
            "covered" : 1,
            "error" : 2,
            "percentage" : 33.3333333333333,
            "total" : 3,
            "uncoverable" : 0
         },
         "statement" : {
            "covered" : 18,
            "percentage" : 100,
            "total" : 18
         },
         "subroutine" : {
            "covered" : 6,
            "percentage" : 100,
            "total" : 6
         },
         "total" : {
            "covered" : 26,
            "error" : 3,
            "percentage" : 89.6551724137931,
            "total" : 29,
            "uncoverable" : 0
         }
      }
   }
}
